sparsekit/sparsekit/__init__.py
sparsekit-0.1.0.dist-info/METADATA
sparsekit-0.1.0.dist-info/WHEEL
sparsekit-0.1.0.dist-info/RECORD
