Metadata-Version: 2.3
Name: sparsekit
Version: 0.1.0
Summary: Sparsity Kit for Structured Sparsity Specification
Author: Ayoub G.
Author-email: research@ayghri.me
Requires-Python: >=3.11,<3.14
Classifier: Programming Language :: Python :: 3
Classifier: Programming Language :: Python :: 3.11
Classifier: Programming Language :: Python :: 3.12
Classifier: Programming Language :: Python :: 3.13
